README.md
ponghat.py
setup.py
ponghat.egg-info/PKG-INFO
ponghat.egg-info/SOURCES.txt
ponghat.egg-info/dependency_links.txt
ponghat.egg-info/top_level.txt
src/__init__.py
src/ai.py
src/ball.py
src/component.py
src/ground.py
src/paddle.py