Metadata-Version: 1.1
Name: ponghat
Version: 1.0.1
Summary: Pong game using functionalities from the Sense HAT
Home-page: https://github.com/rememberYou/ponghat
Author: Terencio Agozzino
Author-email: terencio.agozzino@gmail.com
License: MIT
Project-URL: Source, https://github.com/rememberYou/ponghat
Project-URL: Tracker, https://github.com/rememberYou/ponghat/issues
Keywords: ai emulator game hat mit pong pong-game python sensehat     sense-hat raspberry wall
Platform: UNKNOWN
Classifier: Development Status :: 3 - Alpha
Classifier: License :: OSI Approved :: MIT License
Classifier: Natural Language :: English
Classifier: Programming Language :: Python
Classifier: Programming Language :: Python :: 3.0
Classifier: Programming Language :: Python :: 3.1
Classifier: Programming Language :: Python :: 3.2
Classifier: Programming Language :: Python :: 3.3
Classifier: Programming Language :: Python :: 3.4
Classifier: Programming Language :: Python :: 3.5
Classifier: Programming Language :: Python :: 3.6
Classifier: Programming Language :: Python :: 3.7
Classifier: Programming Language :: Python :: 3 :: Only
Classifier: Topic :: Utilities
